tzlocal/__init__.py
tzlocal/unix.py
tzlocal/utils.py
tzlocal/win32.py
tzlocal/windows_tz.py
tzlocal-5.0.dist-info/LICENSE.txt
tzlocal-5.0.dist-info/METADATA
tzlocal-5.0.dist-info/WHEEL
tzlocal-5.0.dist-info/top_level.txt
tzlocal-5.0.dist-info/zip-safe
tzlocal-5.0.dist-info/RECORD
