Metadata-Version: 2.1
Name: tzlocal
Version: 5.0
Summary: tzinfo object for the local timezone
Home-page: UNKNOWN
Author: Lennart Regebro
Author-email: regebro@gmail.com
License: MIT
Project-URL: Source code, https://github.com/regebro/tzlocal
Project-URL: Issue tracker, https://github.com/regebro/tzlocal/issues
Keywords: timezone
Platform: UNKNOWN
Classifier: Development Status :: 5 - Production/Stable
Classifier: License :: OSI Approved :: MIT License
Classifier: Operating System :: Microsoft :: Windows
Classifier: Operating System :: Unix
Classifier: Operating System :: MacOS :: MacOS X
Classifier: Programming Language :: Python :: 3
Classifier: Programming Language :: Python :: 3 :: Only
Classifier: Programming Language :: Python :: 3.7
Classifier: Programming Language :: Python :: 3.8
Classifier: Programming Language :: Python :: 3.9
Classifier: Programming Language :: Python :: 3.10
Classifier: Programming Language :: Python :: 3.11
Requires-Python: >=3.7
Provides-Extra: devenv
License-File: LICENSE.txt
